LICENSE
README.md
setup.cfg
setup.py
redbookweb/__init__.py
redbookweb/__version__.py
redbookweb/core.py
redbookweb/exception.py
redbookweb/help.py
redbookweb/oss.py
redbookweb.egg-info/PKG-INFO
redbookweb.egg-info/SOURCES.txt
redbookweb.egg-info/dependency_links.txt
redbookweb.egg-info/not-zip-safe
redbookweb.egg-info/requires.txt
redbookweb.egg-info/top_level.txt