Metadata-Version: 2.1
Name: redbookweb
Version: 1.0.1
Summary: redbook web crawl sdk.
Home-page: https://github.com:liusuxian/redbookweb
Author: liusuxian
Author-email: liusuxian89@gmail.com
License: MIT
Keywords: redbookweb crawl
Classifier: Development Status :: 3 - Alpha
Classifier: Intended Audience :: Developers
Classifier: License :: OSI Approved :: MIT License
Classifier: Programming Language :: Python
Classifier: Programming Language :: Python :: 3.8
Classifier: Programming Language :: Python :: 3.9
Classifier: Programming Language :: Python :: 3.10
Classifier: Programming Language :: Python :: 3.11
Classifier: Programming Language :: Python :: 3 :: Only
Classifier: Topic :: Software Development :: Libraries :: Python Modules
Requires-Python: >=3.7
License-File: LICENSE
